wagtail_srcset/__init__.py
wagtail_srcset/apps.py
wagtail_srcset/urls.py
wagtail_srcset/templatetags/wagtail_srcset_tags.py
wagtail_srcset-0.3.0.dist-info/LICENSE
wagtail_srcset-0.3.0.dist-info/WHEEL
wagtail_srcset-0.3.0.dist-info/METADATA
wagtail_srcset-0.3.0.dist-info/RECORD
